mclauncher/__init__.py
mclauncher/__main__.py
mclauncher/main.py
mclauncher/pipe.py
mclauncher/webserver.py
mclauncher/ui/__init__.py
mclauncher/ui/cli.py
mclauncher/ui/gui.py
mclauncher/ui/options.py
pymclauncher-0.1.8.data/scripts/mclauncher
pymclauncher-0.1.8.dist-info/LICENSE
pymclauncher-0.1.8.dist-info/METADATA
pymclauncher-0.1.8.dist-info/WHEEL
pymclauncher-0.1.8.dist-info/top_level.txt
pymclauncher-0.1.8.dist-info/RECORD
