Metadata-Version: 2.1
Name: pymclauncher
Version: 0.1.8
Summary: A minecraft launcher made in python.
Home-page: https://github.com/BobDotCom/mclauncher
Author: BobDotCom
Author-email: bobdotcomgt@gmail.com
License: MIT
Download-URL: https://github.com/BobDotCom/mclauncher/releases
Project-URL: Documentation, https://mclauncher.readthedocs.io/en/latest/index.html
Project-URL: Source, https://github.com/BobDotCom/mclauncher
Project-URL: Tracker, https://github.com/BobDotCom/mclauncher/issues
Platform: UNKNOWN
Classifier: Development Status :: 5 - Production/Stable
Classifier: Programming Language :: Python :: 3
Classifier: License :: OSI Approved :: MIT License
Classifier: Operating System :: OS Independent
Classifier: Programming Language :: Python :: 3.6
Classifier: Programming Language :: Python :: 3.7
Classifier: Programming Language :: Python :: 3.8
Classifier: Programming Language :: Python :: 3.9
Classifier: Programming Language :: Python :: 3.10
Classifier: Topic :: Software Development :: Libraries
Classifier: Topic :: Software Development :: Libraries :: Python Modules
Classifier: Topic :: Utilities
Requires-Python: >=3.6
License-File: LICENSE
Requires-Dist: minecraft-launcher-lib (~=4.1)
Requires-Dist: Flask (>=0.9)
Requires-Dist: requests (!=2.8.0,>=0.8.0)
Requires-Dist: click
